[
    {
        "_id": "wire",
        "init_version": 3,
        "preview": {
            "wordcount": {
                "displayed": false
            },
            "charcount": {
                "displayed": true
            },
            "slugline": {
                "displayed": false
            }
        },
        "details": {
            "wordcount": {
                "displayed": false
            },
            "charcount": {
                "displayed": true
            },
            "slugline": {
                "displayed": false
            }
        },
        "list": {
            "wordcount": {
                "displayed": false
            },
            "charcount": {
                "displayed": true
            },
            "highlights": {
                "urgency": ["#C20000", "#BE8502"]
            }
        },
        "advanced_search_tabs": {},
        "multi_select_topics": false
    },
    {
        "_id": "home",
        "init_version": 3,
        "list": {
            "wordcount": {
                "displayed": false
            },
            "charcount": {
                "displayed": true
            },
            "slugline": {
                "displayed": false
            }
        },
        "details": {
            "wordcount": {
                "displayed": false
            },
            "charcount": {
                "displayed": true
            },
            "slugline": {
                "displayed": false
            }
        }
    }
]
